odoo/addons/account_analytic_line_name_text/README.rst
odoo/addons/account_analytic_line_name_text/__init__.py
odoo/addons/account_analytic_line_name_text/__manifest__.py
odoo/addons/account_analytic_line_name_text/i18n/account_analytic_line_name_text.pot
odoo/addons/account_analytic_line_name_text/i18n/it.po
odoo/addons/account_analytic_line_name_text/models/__init__.py
odoo/addons/account_analytic_line_name_text/models/account_analytic_line.py
odoo/addons/account_analytic_line_name_text/readme/CONTRIBUTORS.md
odoo/addons/account_analytic_line_name_text/readme/DESCRIPTION.md
odoo/addons/account_analytic_line_name_text/static/description/icon.png
odoo/addons/account_analytic_line_name_text/static/description/index.html
odoo_addon_account_analytic_line_name_text-17.0.1.0.0.4.dist-info/METADATA
odoo_addon_account_analytic_line_name_text-17.0.1.0.0.4.dist-info/WHEEL
odoo_addon_account_analytic_line_name_text-17.0.1.0.0.4.dist-info/top_level.txt
odoo_addon_account_analytic_line_name_text-17.0.1.0.0.4.dist-info/RECORD
