Metadata-Version: 2.1
Name: odoo-addon-account_analytic_line_name_text
Version: 17.0.1.0.0.4
Requires-Python: >=3.10
Requires-Dist: odoo>=17.0a,<17.1dev
Summary: Changes account analytic line name field to Text.
Home-page: https://github.com/OCA/account-analytic
License: AGPL-3
Author: Odoo Community Association (OCA), Solvos
Author-email: support@odoo-community.org
Classifier: Programming Language :: Python
Classifier: Framework :: Odoo
Classifier: Framework :: Odoo :: 17.0
Classifier: License :: OSI Approved :: GNU Affero General Public License v3
